rommon/__init__.py
rommon/__main__.py
rommon/Citybrain_Spider/__init__.py
rommon/Citybrain_Spider/gl.py
rommon/Citybrain_Spider/items.py
rommon/Citybrain_Spider/middlewares.py
rommon/Citybrain_Spider/pipelines.py
rommon/Citybrain_Spider/settings.py
rommon/Citybrain_Spider/spiders/__init__.py
rommon/Citybrain_Spider/spiders/city_sp.py
rommon/Citybrain_Spider/utils/__init__.py
rommon/Citybrain_Spider/utils/util.py
datasource_contributor-0.0.14.dist-info/LICENSE
datasource_contributor-0.0.14.dist-info/METADATA
datasource_contributor-0.0.14.dist-info/WHEEL
datasource_contributor-0.0.14.dist-info/entry_points.txt
datasource_contributor-0.0.14.dist-info/top_level.txt
datasource_contributor-0.0.14.dist-info/RECORD
