Metadata-Version: 2.1
Name: datasource-contributor
Version: 0.0.14
Summary: A CUI tool that automatically crawls website data and contributes to http://www.citybrain.org
Home-page: http://112.124.238.90/citybrain/tools/datasource-contributor.git
Author: Hale
Author-email: hao.liang@tianrang-inc.com
License: UNKNOWN
Project-URL: Homepage, http://112.124.238.90/citybrain/tools/datasource-contributor.git
Keywords: git tag datasource-contributor tagup tag-up version autotag auto-tag commit message
Platform: UNKNOWN
Classifier: Programming Language :: Python :: 3
Classifier: License :: OSI Approved :: MIT License
Classifier: Operating System :: OS Independent
Requires-Python: >=3.6
License-File: LICENSE
Requires-Dist: gitpython
Requires-Dist: Scrapy
Requires-Dist: requests
Requires-Dist: fake-useragent
